Metadata-Version: 2.1
Name: mbtasalary
Version: 1.0.0
Summary: Examining MBTA salaries
Home-page: https://github.com/scivision/mbta_salary
Author: Michael Hirsch, Ph.D.
License: UNKNOWN
Keywords: public transportation,MBTA
Platform: UNKNOWN
Classifier: Development Status :: 5 - Production/Stable
Classifier: Environment :: Console
Classifier: Intended Audience :: Science/Research
Classifier: Operating System :: OS Independent
Classifier: Programming Language :: Python :: 3.6
Classifier: Programming Language :: Python :: 3.7
Requires-Python: >= 3.6
Provides-Extra: tests
Provides-Extra: plot
